<?xml version="1.0" encoding="utf-8"?>
<key id="859c6214-2907-47ba-ac0a-7e48a5de88e1" version="1">
  <creationDate>2023-07-16T02:01:06.8359803Z</creationDate>
  <activationDate>2023-07-16T02:01:06.8286187Z</activationDate>
  <expirationDate>2023-10-14T02:01:06.8286187Z</expirationDate>
  <descriptor deserializerType="Microsoft.AspNetCore.DataProtection.AuthenticatedEncryption.ConfigurationModel.AuthenticatedEncryptorDescriptorDeserializer, Microsoft.AspNetCore.DataProtection, Version=6.0.0.0, Culture=neutral, PublicKeyToken=adb9793829ddae60">
    <descriptor>
      <encryption algorithm="AES_256_CBC" />
      <validation algorithm="HMACSHA256" />
      <masterKey p4:requiresEncryption="true" xmlns:p4="http://schemas.asp.net/2015/03/dataProtection">
        <!-- Warning: the key below is in an unencrypted form. -->
        <value>2gDaYlXceDHAhU2KUJG0sws6KmM38H9IYsPyvgitqoRNE+r0U2hkbHkgZ3X+s5zn75bcRiLjJwcMMcbOZ2bKSg==</value>
      </masterKey>
    </descriptor>
  </descriptor>
</key>